SciPipe/__init__.py
SciPipe/_utils.py
SciPipe/data_analysis/__init__.py
SciPipe/data_analysis/eda_analyzer.py
SciPipe/evaluation/__init__.py
SciPipe/evaluation/model_evaluator.py
SciPipe/models/__init__.py
SciPipe/models/xgboost_classification.py
SciPipe/preprocessing/__init__.py
SciPipe/preprocessing/_helpers.py
SciPipe/preprocessing/data_preprocessing.py
SciPipe-0.1.2.dist-info/LICENSE
SciPipe-0.1.2.dist-info/METADATA
SciPipe-0.1.2.dist-info/WHEEL
SciPipe-0.1.2.dist-info/top_level.txt
SciPipe-0.1.2.dist-info/RECORD
